trnamegen/__init__.py
trnamegen/tests.py
trnamegen/data/isimler.csv
trnamegen/data/soyisimler.txt
turkish_name_generator-1.0.4.data/data/isimler.csv
turkish_name_generator-1.0.4.data/data/soyisimler.txt
turkish_name_generator-1.0.4.dist-info/METADATA
turkish_name_generator-1.0.4.dist-info/WHEEL
turkish_name_generator-1.0.4.dist-info/top_level.txt
turkish_name_generator-1.0.4.dist-info/RECORD
