Metadata-Version: 2.1
Name: turkish-name-generator
Version: 1.0.4
Summary: This package generates random Turkish names. You can choose the gender of name and you can get also only first name or last name.
Home-page: https://github.com/MrMirhan/turkish-name-generator
Author: MrMirhan
Author-email: me@mirhan.net
License: MIT
Platform: UNKNOWN
Classifier: Programming Language :: Python :: 3
Classifier: License :: OSI Approved :: MIT License
Classifier: Operating System :: OS Independent
Requires-Dist: pandas
